{"eEWCPn17Hjn3gFjh5OGu4Q==":"namaskar-261x300.png","CGGtf1MuvLFB/KUrA/+mag==":"jumbotron.jpg","ThJd8coBhHnWvBkgiPlobA==":"mbr-1620x1080.jpg","Y11jh84wS/x2vDeukmfxjQ==":"mbr-1-1620x1080.jpg","AuUZg2M/eYEArr1/UOf6lw==":"mbr-2-1620x1080.jpg","Vo4Dz++K/jIU2YTCMuyxKA==":"mbr-1618x1080.jpg","y2w4J1T8n6EEze6bYs7pqQ==":"mbr-3-1620x1080.jpg","iroMHVcchDNywvKBP9jfrA==":"mbr-1626x1080.jpg","dLe1+4gvS0GBTx7Vec+GWg==":"il_fullxfull.326294244-1000x667.jpg","rqk78GiJ2fJ3iGka70UXMg==":"stumpenkerze_gegossen415_1500px_grande-400x287.jpg","RNo13/ZHWx7jehKJB64fvA==":"911793d0ec35d842911d0f43de5adb8c--outdoor-candles-flameless-candles-383x344.jpg","UaP1RJAlMnJ64kY2Wwmv+g==":"mbr-4-1620x1080.jpg","lH1Cndt7GujztjkxMaZzMA==":"412104-1920x1200.jpg","j0gpzitK+6mb5AFknNfkFw==":"438023-1920x1200.jpg","Amf3FqZk6+Wh+QHX/Az0mg==":"438023%20(1)-1024x640.jpg","aSqZQ8kXwIfwe6rATPREAg==":"661688-4695x3183.jpg","mQHkbwxBr0hDrCtFU8/QZg==":"388132-2560x1600.jpg","SVRV4yEphgk6iCtRT6nwwA==":"100-4220-3640x2736.jpg","8p8j/gjwo+ADENgohEzSMg==":"550281-3840x2160.jpg","UVKq81wSy/Uxw9dGSuMA3A==":"434595-2000x1250.jpg","i2Ax+GvgNhj6Y1TDIt1qbw==":"91655-1920x1200.jpg","Y++eJGShsPN2yGE+Zjn1mA==":"tumblr_oh9cvvtls31sxwcnko1-500.gif","XiOIHC7vTzeyYeq/sqKvHA==":"frag-1920x1280.jpg","eKht/oZtZkNuPOxQjYG1fw==":"101633-320x237-perfume-candles-320x237.jpg","PrQFC/eVS1GYFbRZ3XdbYg==":"tumblr_oh9cvvtls31sxwcnko1-501.gif","eMhwyyOCFZPJLXd53RwDZg==":"christmas-2867482-2000x1332.jpg","MnLD1UrEQM7r+r59aS5Naw==":"christmas-2892235-1920-1920x1080.png","Xuk4vaOXIbRhh/zBX+ITzw==":"leaf-2858401-2000x1333.jpg","8QYft2hFH8XoV9byY6WpLQ==":"design-patterns-on-black-bacground-wallpapersbyte-com-1920x1080.jpg","L2pTHIOdsnAvr5DvBm2p9A==":"1559af8e25121df-800x250.jpg","k8b+jW/Fztp9zfk8IgsQ/Q==":"d291e84860e90cf6ba66371de4cd3421.gif","YA4iocRzLv76osaj+3w+gQ==":"black-and-gold-wallpaper-hd-22-wide-wallpaper.gif","5hFBuz95qHqAiEq+KtUSaA==":"black_n_gold_by_manoluv-d3bcwjd-900x563.jpg","jdpnTU0B3SYk3ftk35uoRQ==":"4fb74db4fa3279d8e801513ffc486427--cell-phone-wallpapers-backgrounds-wallpapers-720x1280.jpg","P4ruWcL/RRaS0YZZ1xzNAw==":"floral-pattern-wallpaper-baroque-damask-seamless-vector-background-brown-and-white-ornament_1419-267-626x626.jpg","2L6XcOZwrA4T91voXa4Fjw==":"yes-1024x768.jpg","I2+GJnvoyvqHQYUPdn/lnw==":"1366_768-20100328103833300000-1366x768.jpg","hnuxXpijqW5F28QbEgSZcw==":"christmas-decoration-photo-theme-decorations-ideas-luxurious-kitchen-themed_christmas-decorating-themes_color-change-iphone-app-online-house-designer-fireplace-styles-pictures-decorating-i-1600x1200.jpg","LnEMEunv2pCW081t5aMLpg==":"colorful-background-3-1920x1200.jpg","qJdlKMaLOfa+j2tuETCESg==":"beautiful-colored-animation-with-rotating-floral-decorative-patterns-white-background-full-hd-1080p-1920x1080_4khphlud__f0000-1920x1080.png","6ca22y8PwBa8GaGFcoBlSA==":"patterns_wooden_shape_surface_texture_50887_3840x2160-2000x1125.jpg","QN01nln5jYEg1XGXf1SC7A==":"abstractflowerpattern-1510546791861-2657-1920x1200.jpg","HKIGFPqMB7LhZTIc5VwT/Q==":"fantasyartartworklandscape-1510547160630-4845-2000x1250.jpg","gK/7+0bP/GRaUWfA75HVxQ==":"giphy.gif","jNqCMbQSW1mSO/7ToVH3SQ==":"readytest-12.gif","kBG+5bFp4ZHr57qw0a2pew==":"animated-christmas-greeting-cards3.gif","y8QHwmpqmbuUVuslC/uM+w==":"1%20z14.gif","wzoYxB0RdzcuJl5/597C3Q==":"winter-space-wallpaper-598957.gif","TcuFNEWFrZjZjd0vEDjxFg==":"45229-550x467.jpg","4vhIC0dXmfoMhsDIpi9znw==":"romantic%20tea%20light%20candles%20and%20rose%20preview%20image-590x332.jpg","jEg6aMJO5YSH/H3Djux6Mg==":"165989-1920x1200.jpg","z/s3ynkuTIWGcIvJAahwDA==":"mbr-824x1080.jpg","IU5StFiseKnAmEGxFbd15A==":"crop-620x551.jpg","Skh+J1jlht2U4C9CoB/wDA==":"dark-pattern-wallpaper-full-hd-oww-free-high-resolution-colourful-1920x1200.jpg","AfaA2TdtWzqFd86B7UZFlQ==":"applecinn3pak-1000x1276.jpg","tFB4+Xj6F1+3EDILTKEN2A==":"165989-1-1920x1200.jpg","q7F29tKYq3QXkcKAr4kj0A==":"plain%20votive-2-683x508.jpg","9P7wir2Fj7tQHnWqX9OpeQ==":"tlv3-550x290.jpg","LkVwqdC/anldKggmVlqvEQ==":"mbr-5-1620x1080.jpg","AmMFJznThQv+snv1SAF2dw==":"turquose-votive-holders-m-750x566.jpg","3yS7irvZaqDqMUO3B+2ECw==":"animated-candle-gif-18.gif","2r+m+64ya5wkO3jYl4HQNA==":"03.jpg","1IW715m7dQ2+ThBNpPUgOw==":"02.jpg","EHLXJz30A6msu4l2DcV76A==":"background2.jpg"}